gstreamer_plugins_gpl-1.27.90.data/purelib/gstreamer_plugins_gpl/__init__.py
gstreamer_plugins_gpl-1.27.90.data/purelib/gstreamer_plugins_gpl/bin/dca-0.dll
gstreamer_plugins_gpl-1.27.90.data/purelib/gstreamer_plugins_gpl/bin/dvdnav-4.dll
gstreamer_plugins_gpl-1.27.90.data/purelib/gstreamer_plugins_gpl/bin/dvdread-8.dll
gstreamer_plugins_gpl-1.27.90.data/purelib/gstreamer_plugins_gpl/lib/gstreamer-1.0/gsta52dec.dll
gstreamer_plugins_gpl-1.27.90.data/purelib/gstreamer_plugins_gpl/lib/gstreamer-1.0/gstdtsdec.dll
gstreamer_plugins_gpl-1.27.90.data/purelib/gstreamer_plugins_gpl/lib/gstreamer-1.0/gstdvdread.dll
gstreamer_plugins_gpl-1.27.90.data/purelib/gstreamer_plugins_gpl/lib/gstreamer-1.0/gstresindvd.dll
gstreamer_plugins_gpl-1.27.90.dist-info/METADATA
gstreamer_plugins_gpl-1.27.90.dist-info/WHEEL
gstreamer_plugins_gpl-1.27.90.dist-info/top_level.txt
gstreamer_plugins_gpl-1.27.90.dist-info/RECORD
