Metadata-Version: 2.4
Name: gstreamer_plugins_gpl
Version: 1.27.90
Summary: GStreamer 1.0
Home-page: http://gstreamer.freedesktop.org
Author: GStreamer Project
License: MIT AND LGPL-2.0-or-later AND GPL-2.0-or-later AND LGPL-2.1-or-later AND BSD-3-Clause AND Apache-2.0
Classifier: Development Status :: 4 - Beta
Classifier: Intended Audience :: Developers
Classifier: Programming Language :: Python :: 3
Classifier: Topic :: Multimedia :: Graphics
Classifier: Topic :: Multimedia :: Sound/Audio
Classifier: Topic :: Multimedia :: Video
Classifier: Topic :: Software Development
Classifier: Topic :: Utilities
Classifier: Environment :: MacOS X
Classifier: Operating System :: MacOS :: MacOS X
Classifier: Environment :: Win32 (MS Windows)
Classifier: Operating System :: Microsoft :: Windows
Requires-Python: >= 3.14
Requires-Dist: gstreamer_plugins_runtime~=1.27.90
Dynamic: author
Dynamic: classifier
Dynamic: home-page
Dynamic: license
Dynamic: requires-dist
Dynamic: requires-python
Dynamic: summary
